devchat_ask-0.1.11.dist-info/WHEEL
devchat_ask-0.1.11.dist-info/RECORD
devchat_ask-0.1.11.dist-info/METADATA
chat/__init__.cpython-311-x86_64-linux-gnu.so
chat/README.md
chat/interaction/__init__.cpython-311-x86_64-linux-gnu.so
chat/interaction/executor.cpython-311-x86_64-linux-gnu.so
chat/evaluation/retrieval/example.cpython-311-x86_64-linux-gnu.so
chat/evaluation/retrieval/retrieval_eval.cpython-311-x86_64-linux-gnu.so
chat/evaluation/retrieval/data/code_search_net_eval/scores.csv
chat/evaluation/retrieval/data/code_search_net_eval/snippets.zip
chat/evaluation/retrieval/data/code_search_net_eval/README.md
chat/evaluation/retrieval/data/code_search_net_eval/load.cpython-311-x86_64-linux-gnu.so
chat/evaluation/qa/util.cpython-311-x86_64-linux-gnu.so
chat/evaluation/qa/evaluation.cpython-311-x86_64-linux-gnu.so
chat/evaluation/qa/__init__.cpython-311-x86_64-linux-gnu.so
chat/evaluation/qa/question_set.cpython-311-x86_64-linux-gnu.so
chat/evaluation/qa/README.md
chat/evaluation/qa/cli.cpython-311-x86_64-linux-gnu.so
chat/evaluation/qa/report.cpython-311-x86_64-linux-gnu.so
chat/evaluation/qa/evaluable/smart_qa.cpython-311-x86_64-linux-gnu.so
chat/evaluation/qa/evaluable/__init__.cpython-311-x86_64-linux-gnu.so
chat/evaluation/qa/evaluable/base.cpython-311-x86_64-linux-gnu.so
chat/evaluation/qa/evaluable/yes_no.cpython-311-x86_64-linux-gnu.so
chat/evaluation/qa/evaluator/manual.cpython-311-x86_64-linux-gnu.so
chat/evaluation/qa/evaluator/rating.cpython-311-x86_64-linux-gnu.so
chat/evaluation/qa/evaluator/correctness.cpython-311-x86_64-linux-gnu.so
chat/evaluation/qa/evaluator/__init__.cpython-311-x86_64-linux-gnu.so
chat/evaluation/qa/evaluator/base.cpython-311-x86_64-linux-gnu.so
chat/evaluation/qa/evaluator/llm_helper/rate_it.cpython-311-x86_64-linux-gnu.so
chat/evaluation/qa/evaluator/llm_helper/conf.cpython-311-x86_64-linux-gnu.so
chat/evaluation/qa/evaluator/llm_helper/judge_single.cpython-311-x86_64-linux-gnu.so
chat/evaluation/qa/evaluator/llm_helper/__init__.cpython-311-x86_64-linux-gnu.so
