Metadata-Version: 2.1
Name: devchat-ask
Version: 0.1.11
Summary: 
Author: Hezheng Yin
Author-email: hezheng@merico.dev
Requires-Python: >=3.11,<3.12
Classifier: Programming Language :: Python :: 3
Classifier: Programming Language :: Python :: 3.11
Requires-Dist: click (>=8.1.7,<9.0.0)
Requires-Dist: gitpython (>=3.1.40,<4.0.0)
Requires-Dist: httpx (>=0.24.1,<0.25.0)
Requires-Dist: langchain (==0.0.339)
Requires-Dist: loguru (>=0.7.0,<0.8.0)
Requires-Dist: openai (>=1.3.4,<2.0.0)
Requires-Dist: pathspec (>=0.11.2,<0.12.0)
Requires-Dist: python-dotenv (>=1.0.0,<2.0.0)
Requires-Dist: tenacity (>=8.2.3,<9.0.0)
Requires-Dist: tiktoken (>=0.3.3,<0.4.0)
Requires-Dist: uuid (>=1.30,<2.0)
